tool_tray/__init__.py
tool_tray/__main__.py
tool_tray/autostart.py
tool_tray/config.py
tool_tray/desktop.py
tool_tray/log_viewer.py
tool_tray/logging.py
tool_tray/manifest.py
tool_tray/setup_dialog.py
tool_tray/state.py
tool_tray/tray.py
tool_tray/update_dialog.py
tool_tray/updater.py
tool_tray-0.3.19.dist-info/WHEEL
tool_tray-0.3.19.dist-info/entry_points.txt
tool_tray-0.3.19.dist-info/METADATA
tool_tray-0.3.19.dist-info/RECORD
