Metadata-Version: 2.3
Name: tool-tray
Version: 0.3.19
Summary: System tray tool manager for private GitHub tools via uv
Author: Fredrik Averpil
Author-email: Fredrik Averpil <fredrik.averpil@gmail.com>
Requires-Dist: httpx>=0.28.1
Requires-Dist: pillow>=12.1.0
Requires-Dist: pyshortcuts>=1.9.7
Requires-Dist: pystray>=0.19.5
Requires-Python: >=3.12
